{
	"parent": "minecraft:block/thin_block",
	"ambientocclusion": false,
	"textures": {
		"0": "automobility:block/dash_panel_off",
		"1": "automobility:block/dash_panel_frame",
		"particle": "automobility:block/dash_panel_off"
	},
	"elements": [
		{
			"from": [0, 0, 1],
			"to": [16, 1, 15],
			"faces": {
				"north": {"uv": [1, 0, 15, 1], "texture": "#0"},
				"east": {"uv": [1, 15, 15, 16], "texture": "#0"},
				"south": {"uv": [1, 15, 15, 16], "texture": "#0"},
				"west": {"uv": [1, 0, 15, 1], "texture": "#0"},
				"up": {"uv": [0, 1, 16, 15], "texture": "#0"},
				"down": {"uv": [0, 1, 16, 15], "texture": "#0"}
			}
		},
		{
			"from": [0, 0, 0],
			"to": [16, 1, 1],
			"faces": {
				"north": {"uv": [0, 0, 16, 1], "texture": "#1"},
				"east": {"uv": [15, 0, 16, 1], "texture": "#1"},
				"south": {"uv": [0, 0, 16, 1], "texture": "#1"},
				"west": {"uv": [0, 0, 1, 1], "texture": "#1"},
				"up": {"uv": [0, 0, 16, 1], "texture": "#1"},
				"down": {"uv": [0, 0, 16, 1], "texture": "#1"}
			}
		},
		{
			"from": [0, 0, 15],
			"to": [16, 1, 16],
			"faces": {
				"north": {"uv": [0, 0, 16, 1], "texture": "#1"},
				"east": {"uv": [15, 15, 16, 16], "texture": "#1"},
				"south": {"uv": [0, 15, 16, 16], "texture": "#1"},
				"west": {"uv": [0, 15, 1, 16], "texture": "#1"},
				"up": {"uv": [0, 15, 16, 16], "texture": "#1"},
				"down": {"uv": [0, 0, 16, 1], "texture": "#1"}
			}
		}
	]
}